HISTORY.txt
README.txt
setup.py
corejet/__init__.py
corejet.recipe.testrunner.egg-info/PKG-INFO
corejet.recipe.testrunner.egg-info/SOURCES.txt
corejet.recipe.testrunner.egg-info/dependency_links.txt
corejet.recipe.testrunner.egg-info/entry_points.txt
corejet.recipe.testrunner.egg-info/namespace_packages.txt
corejet.recipe.testrunner.egg-info/not-zip-safe
corejet.recipe.testrunner.egg-info/requires.txt
corejet.recipe.testrunner.egg-info/top_level.txt
corejet/recipe/__init__.py
corejet/recipe/testrunner/__init__.py