Metadata-Version: 1.0
Name: corejet.recipe.testrunner
Version: 1.0.0
Summary: ZC Buildout recipe for creating CoreJet test runners
Home-page: https://github.com/datakurre/corejet.recipe.testrunner/
Author: Asko Soukka
Author-email: asko.soukka@iki.fi
License: ZPL 2.1
Keywords: corejet recipe
Platform: UNKNOWN
Classifier: Programming Language :: Python
